weldkit/__init__.py
weldkit/cli.py
weldkit/core/__init__.py
weldkit/intergrations/__init__.py
weldkit-0.1.1.dist-info/METADATA
weldkit-0.1.1.dist-info/WHEEL
weldkit-0.1.1.dist-info/top_level.txt
weldkit-0.1.1.dist-info/RECORD
